Metadata-Version: 2.1
Name: odoo13-addon-l10n-es-aeat-mod190
Version: 13.0.1.1.2
Summary: AEAT modelo 190
Home-page: https://github.com/OCA/l10n-spain
Author: Punt Sistemes SLU,Odoo Community Association (OCA),Vunkers IT Experts, SLU
Author-email: support@odoo-community.org
License: AGPL-3
Platform: UNKNOWN
Classifier: Programming Language :: Python
Classifier: Framework :: Odoo
Classifier: Framework :: Odoo :: 13.0
Classifier: License :: OSI Approved :: GNU Affero General Public License v3
Requires-Python: >=3.5
Requires-Dist: odoo13-addon-l10n-es-aeat
Requires-Dist: odoo (<13.1dev,>=13.0a)
